ofdcomparer/__init__.py
ofdcomparer/compare_ffd.py
ofdcomparer/configs.py
ofdcomparer/convert.py
ofdcomparer/dto10.py
ofdcomparer/dto_error_descriptions.py
ofdcomparer/helpers.py
ofdcomparer/libfptr10.py
ofdcomparer/ofd_cri_atol.py
ofdcomparer/ofd_taxcom.py
ofdcomparer/tags_fn.py
ofdcomparer-0.0.3.dist-info/LICENSE
ofdcomparer-0.0.3.dist-info/METADATA
ofdcomparer-0.0.3.dist-info/WHEEL
ofdcomparer-0.0.3.dist-info/top_level.txt
ofdcomparer-0.0.3.dist-info/RECORD
