Metadata-Version: 2.1
Name: ofdcomparer
Version: 0.0.3
Summary: Библиотека для сравнивания ФД из ФН и ОФД
Author-email: k.kabisova@atol.ru
Classifier: License :: OSI Approved :: MIT License
Classifier: Programming Language :: Python :: 3
Classifier: Programming Language :: Python :: 3.6
Classifier: Programming Language :: Python :: 3.7
Classifier: Programming Language :: Python :: 3.8
Classifier: Programming Language :: Python :: 3.9
License-File: LICENSE
Requires-Dist: requests ==2.31.0
Requires-Dist: requests-toolbelt ==1.0.0
Requires-Dist: urllib3 ==2.0.6
Requires-Dist: zipp ==3.17.0
